modasci/VERSION
modasci/__init__.py
modasci/__main__.py
modasci/cli.py
modasci/data_connector.py
modasci/data_handler.py
modasci/path.py
modasci/serialization.py
modasci/storage.py
modasci/workflow.py
modasci/persistents/__init__.py
modasci/persistents/base.py
modasci/persistents/reference.py
modasci/tasks/__init__.py
modasci/tasks/base.py
modasci/tasks/micro.py
modasci/tasks/task.py
modasci/volatiles/__init__.py
modasci/volatiles/base.py
modasci/volatiles/pandas_dataframe.py
modasci-0.0.2.dist-info/LICENSE
modasci-0.0.2.dist-info/METADATA
modasci-0.0.2.dist-info/WHEEL
modasci-0.0.2.dist-info/top_level.txt
modasci-0.0.2.dist-info/RECORD
