Metadata-Version: 2.1
Name: modasci
Version: 0.0.2
Summary: Easy Logging Utility
Home-page: https://github.com/ArashLab/modasci
Author: Arash Bayat
Author-email: a.bayat@garvan.org.au
License: MIT
Platform: UNKNOWN
Classifier: Programming Language :: Python :: 3
